{
  "project_info": {
    "project_number": "210171558323",
    "project_id": "viplabcovertest-ade03",
    "storage_bucket": "viplabcovertest-ade03.appspot.com"
  },
  "client": [
    {
      "client_info": {
        "mobilesdk_app_id": "1:210171558323:android:f7d95f8b387ad905c8f3c6",
        "android_client_info": {
          "package_name": "com.example.viplabprojeto"
        }
      },
      "oauth_client": [
        {
          "client_id": "210171558323-r4egvgn5rufqaedhf9fat4l7its1b4lv.apps.googleusercontent.com",
          "client_type": 3
        }
      ],
      "api_key": [
        {
          "current_key": "AIzaSyAZ-kLyd2fOScf9f5ChuLmvdvg7g4GHyEs"
        }
      ],
      "services": {
        "appinvite_service": {
          "other_platform_oauth_client": [
            {
              "client_id": "210171558323-r4egvgn5rufqaedhf9fat4l7its1b4lv.apps.googleusercontent.com",
              "client_type": 3
            }
          ]
        }
      }
    }
  ],
  "configuration_version": "1"
}